typed_ast/__init__.py
typed_ast/_ast27.cpython-37m-darwin.so
typed_ast/_ast3.cpython-37m-darwin.so
typed_ast/ast27.py
typed_ast/ast3.py
typed_ast/conversions.py
typed_ast/tests/test_basics.py
typed_ast-1.5.3.dist-info/LICENSE
typed_ast-1.5.3.dist-info/METADATA
typed_ast-1.5.3.dist-info/WHEEL
typed_ast-1.5.3.dist-info/top_level.txt
typed_ast-1.5.3.dist-info/RECORD
