Metadata-Version: 2.1
Name: typed_ast
Version: 1.5.3
Summary: a fork of Python 2 and 3 ast modules with type comment support
Home-page: https://github.com/python/typed_ast
Author: David Fisher
License: Apache License 2.0
Platform: POSIX
Platform: Windows
Classifier: Development Status :: 5 - Production/Stable
Classifier: Environment :: Console
Classifier: Intended Audience :: Developers
Classifier: Operating System :: POSIX
Classifier: Operating System :: Microsoft
Classifier: Programming Language :: Python :: 3.6
Classifier: Programming Language :: Python :: 3.7
Classifier: Programming Language :: Python :: 3.8
Classifier: Programming Language :: Python :: 3.9
Classifier: Programming Language :: Python :: 3.10
Classifier: Topic :: Software Development
Requires-Python: >=3.6
License-File: LICENSE
